CHANGELOG.md
netsm/__init__.py
netsm/cli.py
netsm/core.py
netsm/gui.py
netsm-0.1.5.dist-info/entry_points.txt
netsm-0.1.5.dist-info/LICENSE
netsm-0.1.5.dist-info/WHEEL
netsm-0.1.5.dist-info/METADATA
netsm-0.1.5.dist-info/RECORD
